fyler/__init__.py
fyler/__main__.py
fyler/application.py
fyler/models.py
fyler/settings_handler.py
fyler/utils.py
fyler/assets/__init__.py
fyler/assets/advancedwindow.ui
fyler/assets/mainwindow.ui
fyler/assets/searchwindow.ui
fyler/assets/settingswindow.ui
fyler/providers/__init__.py
fyler/providers/anidb.py
fyler/providers/anilist.py
fyler/providers/provider.py
fyler/providers/thetvdb.py
fyler/views/__init__.py
fyler/views/advanced_window.py
fyler/views/main_window.py
fyler/views/search_window.py
fyler/views/settings_window.py
fyler-0.1.1.dist-info/LICENSE
fyler-0.1.1.dist-info/METADATA
fyler-0.1.1.dist-info/WHEEL
fyler-0.1.1.dist-info/entry_points.txt
fyler-0.1.1.dist-info/top_level.txt
fyler-0.1.1.dist-info/RECORD
