Metadata-Version: 2.1
Name: fyler
Version: 0.1.1
Summary: An application to help organize TV Shows/Anime/Movies
Home-page: UNKNOWN
Author: Alex Gonzales
License: UNKNOWN
Platform: UNKNOWN
Requires-Python: >=3.8.0
Requires-Dist: PyQT5
Requires-Dist: appdirs
Requires-Dist: beautifulsoup4
Requires-Dist: diskcache
Requires-Dist: fuzzywuzzy[speedup]
Requires-Dist: lxml
Requires-Dist: ratelimit
Requires-Dist: requests
